pymeasurement/__init__.py
pymeasurement/measurement.py
pymeasurement/sigfig.py
pymeasurement/util/parser.py
pymeasurement/util/typecheck.py
pymeasurement/util/chem/compound.py
pymeasurement/util/chem/element.py
pymeasurement-1.1.4.dist-info/METADATA
pymeasurement-1.1.4.dist-info/WHEEL
pymeasurement-1.1.4.dist-info/licenses/LICENSE
pymeasurement-1.1.4.dist-info/RECORD
